{
  "schemaVersion": 1,
  "taskId": "T01",
  "unitId": "M013/S02/T01",
  "timestamp": 1775571638731,
  "passed": true,
  "discoverySource": "task-plan",
  "checks": [
    {
      "command": "npx next build",
      "exitCode": 0,
      "durationMs": 19776,
      "verdict": "pass"
    },
    {
      "command": "grep -q 'captureException' src/app/error.tsx",
      "exitCode": 0,
      "durationMs": 10,
      "verdict": "pass"
    },
    {
      "command": "grep -q 'captureException' src/app/global-error.tsx",
      "exitCode": 0,
      "durationMs": 5,
      "verdict": "pass"
    },
    {
      "command": "grep -q 'useEffect' src/app/global-error.tsx",
      "exitCode": 0,
      "durationMs": 6,
      "verdict": "pass"
    }
  ]
}
